<?xml version="1.0" encoding="utf-8" ?><dwsync><file name="flaticon.css" server="ps16781.dreamhost.com/kittylikesavocado.premiumdw.com/" local="3517594918" remote="3517594919" Dst="-1" /><file name="flaticon.eot" server="ps16781.dreamhost.com/kittylikesavocado.premiumdw.com/" local="3517625920" remote="3517594881" Dst="-1" /><file name="flaticon.html" server="ps16781.dreamhost.com/kittylikesavocado.premiumdw.com/" local="3517625920" remote="3517594881" Dst="-1" /><file name="flaticon.svg" server="ps16781.dreamhost.com/kittylikesavocado.premiumdw.com/" local="3517625920" remote="3517594882" Dst="-1" /><file name="flaticon.ttf" server="ps16781.dreamhost.com/kittylikesavocado.premiumdw.com/" local="3517625920" remote="3517594882" Dst="-1" /><file name="flaticon.woff" server="ps16781.dreamhost.com/kittylikesavocado.premiumdw.com/" local="3517625920" remote="3517594883" Dst="-1" /><file name="license.txt" server="ps16781.dreamhost.com/kittylikesavocado.premiumdw.com/" local="3517625920" remote="3517594883" Dst="-1" /><file name="flaticon.css" server="ftp.braingrenadeentertainment.com/public_html/kittylikesavocado/" local="3517594918" remote="3517788540" Dst="-1" /><file name="flaticon.eot" server="ftp.braingrenadeentertainment.com/public_html/kittylikesavocado/" local="3517625920" remote="3517788540" Dst="-1" /><file name="flaticon.html" server="ftp.braingrenadeentertainment.com/public_html/kittylikesavocado/" local="3517625920" remote="3517788540" Dst="-1" /><file name="flaticon.svg" server="ftp.braingrenadeentertainment.com/public_html/kittylikesavocado/" local="3517625920" remote="3517788540" Dst="-1" /><file name="flaticon.ttf" server="ftp.braingrenadeentertainment.com/public_html/kittylikesavocado/" local="3517625920" remote="3517788540" Dst="-1" /><file name="flaticon.woff" server="ftp.braingrenadeentertainment.com/public_html/kittylikesavocado/" local="3517625920" remote="3517788540" Dst="-1" /><file name="license.txt" server="ftp.braingrenadeentertainment.com/public_html/kittylikesavocado/" local="3517625920" remote="3517788540" Dst="-1" /></dwsync>